[{"__symbolic":"module","version":4,"metadata":{"JsonFormComponent":{"__symbolic":"class","decorators":[{"__symbolic":"call","expression":{"__symbolic":"reference","module":"@angular/core","name":"Component","line":8,"character":1},"arguments":[{"selector":"jf-form","template":"\n    <form\n      [formGroup]=\"form\"\n      (ngSubmit)=\"handleOnSubmit()\"\n      *ngIf=\"isValidSchema()\"\n    >\n      <div jf-component-chooser\n           [class]=\"outerClass\"\n           [form]=\"form\"\n           [submitted]=\"submitted\"\n           [schema]=\"schema\">\n      </div>\n      <div #ref>\n        <ng-content></ng-content>\n      </div>\n      <div\n        *ngIf=\"ref.children.length == 0\"\n        [ngClass]=\"{\n             'margin-top--double': true,\n             'page-actions--edges': (cancel && submit),\n             'page-actions--center': (!cancel || !submit)\n           }\">\n        <button\n          type=\"button\"\n          [ngClass]=\"['btn btn-default button', cancelClass]\"\n          *ngIf=\"cancel\"\n          [disabled]=\"isWorking\"\n          (click)=\"handleOnCancel()\">{{cancel}}</button>\n        <button\n          type=\"submit\"\n          [ngClass]=\"['btn btn-primary button button--accept', submitClass]\"\n          *ngIf=\"submit\"\n          [disabled]=\"isWorking\"\n        >\n            <svg *ngIf=\"isWorking\" width=\"38\" height=\"38\" viewBox=\"0 0 38 38\" xmlns=\"http://www.w3.org/2000/svg\" stroke=\"#fff\">\n              <g fill=\"none\" fill-rule=\"evenodd\">\n                <g transform=\"translate(1 1)\" stroke-width=\"2\">\n                  <circle stroke-opacity=\".5\" cx=\"18\" cy=\"18\" r=\"18\"/>\n                  <path d=\"M36 18c0-9.94-8.06-18-18-18\">\n                    <animateTransform\n                      attributeName=\"transform\"\n                      type=\"rotate\"\n                      from=\"0 18 18\"\n                      to=\"360 18 18\"\n                      dur=\"1s\"\n                      repeatCount=\"indefinite\"/>\n                  </path>\n                </g>\n              </g>\n            </svg>\n            {{submit}}\n        </button>\n      </div>\n    </form>\n  "}]}],"members":{"schema":[{"__symbolic":"property","decorators":[{"__symbolic":"call","expression":{"__symbolic":"reference","module":"@angular/core","name":"Input","line":67,"character":3}}]}],"data":[{"__symbolic":"property","decorators":[{"__symbolic":"call","expression":{"__symbolic":"reference","module":"@angular/core","name":"Input","line":69,"character":3}}]}],"style":[{"__symbolic":"property","decorators":[{"__symbolic":"call","expression":{"__symbolic":"reference","module":"@angular/core","name":"Input","line":71,"character":3}}]}],"submit":[{"__symbolic":"property","decorators":[{"__symbolic":"call","expression":{"__symbolic":"reference","module":"@angular/core","name":"Input","line":73,"character":3}}]}],"cancel":[{"__symbolic":"property","decorators":[{"__symbolic":"call","expression":{"__symbolic":"reference","module":"@angular/core","name":"Input","line":75,"character":3}}]}],"outerClass":[{"__symbolic":"property","decorators":[{"__symbolic":"call","expression":{"__symbolic":"reference","module":"@angular/core","name":"Input","line":77,"character":3}}]}],"submitClass":[{"__symbolic":"property","decorators":[{"__symbolic":"call","expression":{"__symbolic":"reference","module":"@angular/core","name":"Input","line":79,"character":3}}]}],"cancelClass":[{"__symbolic":"property","decorators":[{"__symbolic":"call","expression":{"__symbolic":"reference","module":"@angular/core","name":"Input","line":81,"character":3}}]}],"isWorking":[{"__symbolic":"property","decorators":[{"__symbolic":"call","expression":{"__symbolic":"reference","module":"@angular/core","name":"Input","line":83,"character":3}}]}],"handleSubmit":[{"__symbolic":"property","decorators":[{"__symbolic":"call","expression":{"__symbolic":"reference","module":"@angular/core","name":"Output","line":85,"character":3}}]}],"handleChange":[{"__symbolic":"property","decorators":[{"__symbolic":"call","expression":{"__symbolic":"reference","module":"@angular/core","name":"Output","line":87,"character":3}}]}],"handleCancel":[{"__symbolic":"property","decorators":[{"__symbolic":"call","expression":{"__symbolic":"reference","module":"@angular/core","name":"Output","line":89,"character":3}}]}],"__ctor__":[{"__symbolic":"constructor","parameterDecorators":[[{"__symbolic":"call","expression":{"__symbolic":"reference","module":"@angular/core","name":"Inject","line":102,"character":5},"arguments":[{"__symbolic":"reference","module":"@angular/forms","name":"FormBuilder","line":102,"character":12}]}],null,null],"parameters":[{"__symbolic":"reference","module":"@angular/forms","name":"FormBuilder","line":102,"character":29},{"__symbolic":"reference","module":"./services/validators.service","name":"JsonFormValidatorsService","line":103,"character":15},{"__symbolic":"reference","module":"./services/defaults.service","name":"JsonFormDefaultsService","line":104,"character":15}]}],"ngOnInit":[{"__symbolic":"method"}],"ngDoCheck":[{"__symbolic":"method"}],"ngOnDestroy":[{"__symbolic":"method"}],"constructForm":[{"__symbolic":"method"}],"isValidSchema":[{"__symbolic":"method"}],"generateForm":[{"__symbolic":"method"}],"isOneOf":[{"__symbolic":"method"}],"inOneOf":[{"__symbolic":"method"}],"isVisible":[{"__symbolic":"method"}],"isFormat":[{"__symbolic":"method"}],"handleOnSubmit":[{"__symbolic":"method"}],"handleOnChange":[{"__symbolic":"method"}],"handleOnCancel":[{"__symbolic":"method"}],"subRefs":[{"__symbolic":"method"}]}}}}]